README.md
setup.py
ecotool/__init__.py
ecotool/_version.py
ecotool.egg-info/PKG-INFO
ecotool.egg-info/SOURCES.txt
ecotool.egg-info/dependency_links.txt
ecotool.egg-info/top_level.txt
ecotool/common/__init__.py
ecotool/common/asset.py