Metadata-Version: 1.0
Name: ecotool
Version: 0.0.2
Summary: Tools for Economic Applications
Home-page: UNKNOWN
Author: chenjiahui
Author-email: chenjiahui1991@163.com
License: MIT Licence
Platform: UNKNOWN
